CHANGELOG
LICENSE
MANIFEST.in
Makefile
README.md
setup.cfg
setup.py
storm/__init__.py
storm/base.py
storm/cache.py
storm/cextensions.c
storm/compat.py
storm/database.py
storm/event.py
storm/exceptions.py
storm/expr.py
storm/info.py
storm/locals.py
storm/properties.py
storm/references.py
storm/store.py
storm/tracer.py
storm/tz.py
storm/uri.py
storm/variables.py
storm/xid.py
storm/databases/__init__.py
storm/databases/postgres.py
storm/databases/sqlite.py
storm_legacy.egg-info/PKG-INFO
storm_legacy.egg-info/SOURCES.txt
storm_legacy.egg-info/dependency_links.txt
storm_legacy.egg-info/not-zip-safe
storm_legacy.egg-info/requires.txt
storm_legacy.egg-info/top_level.txt
tests/__init__.py
tests/base.py
tests/database.py
tests/helper.py
tests/mocker.py
tests/test_cache.py
tests/test_doc.py
tests/test_event.py
tests/test_expr.py
tests/test_info.py
tests/test_properties.py
tests/test_tracer.py
tests/test_uri.py
tests/test_variables.py
tests/databases/__init__.py
tests/databases/base.py
tests/databases/postgres.py
tests/databases/proxy.py
tests/databases/sqlite.py
tests/store/__init__.py
tests/store/base.py
tests/store/postgres.py
tests/store/sqlite.py