Metadata-Version: 2.1
Name: storm-legacy
Version: 0.2.0
Summary: Storm is an object-relational mapper (ORM) for Python developed at Canonical. This is a fork maintained by Andreas Runfalk
Home-page: https://github.com/runfalk/storm-legacy
Author: Gustavo Niemeyer
Author-email: gustavo@niemeyer.net
Maintainer: Andreas Runfalk
Maintainer-email: andreas@runfalk.se
License: LGPL
Download-URL: https://pypi.org/project/storm-legacy/
Platform: UNKNOWN
Classifier: Development Status :: 5 - Production/Stable
Classifier: Intended Audience :: Developers
Classifier: License :: OSI Approved :: GNU Library or Lesser General Public License (LGPL)
Classifier: Programming Language :: Python
Classifier: Programming Language :: Python :: 2.7
Classifier: Programming Language :: Python :: 3.3
Classifier: Programming Language :: Python :: 3.4
Classifier: Programming Language :: Python :: 3.5
Classifier: Programming Language :: Python :: 3.6
Classifier: Programming Language :: Python :: 3.7
Classifier: Topic :: Database
Classifier: Topic :: Database :: Front-Ends
Classifier: Topic :: Software Development :: Libraries :: Python Modules
Provides-Extra: doc
Provides-Extra: dev
